kahi_ranking_udea_works/Kahi_ranking_udea_works.py
kahi_ranking_udea_works/__init__.py
kahi_ranking_udea_works/_version.py
kahi_ranking_udea_works/parser.py
kahi_ranking_udea_works/process_one.py
Kahi_ranking_udea_works-0.1.4b0.dist-info/LICENSE
Kahi_ranking_udea_works-0.1.4b0.dist-info/METADATA
Kahi_ranking_udea_works-0.1.4b0.dist-info/WHEEL
Kahi_ranking_udea_works-0.1.4b0.dist-info/top_level.txt
Kahi_ranking_udea_works-0.1.4b0.dist-info/RECORD
